cami_opal/__init__.py
cami_opal/binary_metrics.py
cami_opal/braycurtis.py
cami_opal/evaluate.py
cami_opal/html_opal.py
cami_opal/l1norm.py
cami_opal/plots.py
cami_opal/rankings.py
cami_opal/shannon.py
cami_opal/tsv2biom.py
cami_opal/unifrac_distance.py
cami_opal/utils/EMDUnifrac.py
cami_opal/utils/ProfilingTools.py
cami_opal/utils/ProfilingToolsABC.py
cami_opal/utils/ProfilingToolsCAMI.py
cami_opal/utils/__init__.py
cami_opal/utils/constants.py
cami_opal/utils/load_data.py
cami_opal/utils/spider_plot_functions.py
cami_opal-1.0.13.data/scripts/opal.py
cami_opal-1.0.13.data/scripts/opal_stats.py
cami_opal-1.0.13.data/scripts/opal_workflow.py
cami_opal-1.0.13.data/scripts/setup.py
cami_opal-1.0.13.data/scripts/version.py
cami_opal-1.0.13.dist-info/LICENSE
cami_opal-1.0.13.dist-info/METADATA
cami_opal-1.0.13.dist-info/WHEEL
cami_opal-1.0.13.dist-info/top_level.txt
cami_opal-1.0.13.dist-info/RECORD
