Metadata-Version: 2.1
Name: cami-opal
Version: 1.0.13
Summary: OPAL: Open-community Profiling Assessment tooL
Home-page: http://cami-challenge.org
Author: CAMI
Author-email: support@cami-challenge.org
License: Apache-2.0 License
Classifier: Natural Language :: English
Classifier: License :: OSI Approved :: Apache Software License
Classifier: Programming Language :: Python
Classifier: Programming Language :: Python :: 3.11
Classifier: Topic :: Scientific/Engineering :: Bio-Informatics
Classifier: Intended Audience :: Science/Research
Classifier: Operating System :: POSIX
License-File: LICENSE
Requires-Dist: numpy (==2.0.1)
Requires-Dist: matplotlib (==3.8.4)
Requires-Dist: pandas (==2.2.2)
Requires-Dist: jinja2 (==3.1.4)
Requires-Dist: bokeh (==3.5.1)
Requires-Dist: seaborn (==0.13.2)
Requires-Dist: docker (==6.1.2)
Requires-Dist: scipy (==1.14.0)
